{
  "28": "(",
  "29": ")",
  "10181": "All",
  "4515799": "LINKS",
  "66639742": "Morbi commodo congue viverra. Donec metus mauris, ultrices ut dapibus sed, aliquet vel ligula. Pellentesque hendrerit arcu quam",
  "-4499f4e1": "Artworks",
  "1fa3c2": "Blog",
  "3c2336d": "About",
  "-64104400": "Contact",
  "5e918d2": "hello",
  "-2c24e49c": "I'm Chizaram",
  "63ae4973": "chizaram",
  "-3d912403": "I'm a design-minded front-end software engineer focused on building beautiful interfaces & experiences",
  "792b2792": "Instagram",
  "2c9a4253": "Twitter",
  "4b0ff51e": "Linkedin",
  "6c03005d": "chizaram@rd3studio.com",
  "a0f5": "(WD",
  "3d503d2b": "No items found.",
  "-5274ffbe": "I’m a software engineer based in Houston Also a freelancer at ",
  "66958d37": "Rd3studio",
  "2e": ".",
  "-191fcfa0": "EDUCATION/CERTIFICATIONS",
  "-33462c62": "Western Governor Univeristy",
  "38a56e8d": "BSc Computer Science",
  "-739a2b9a": "Amazon Web Services",
  "7ffa52c9": "AWS Solutions Architect - associate ",
  "-1dc797d7": "EXPERIENCES",
  "-7b5c0594": "KROGER",
  "5e07f106": "Frontend Software Engineer ",
  "1dd27a02": "BESTBUY",
  "-54ab44e3": "FullStack Developer ",
  "97e7fb": "LANGUAGES",
  "-709ce304": "Python",
  "57b068a5": "Typescript",
  "-54a68350": "HTML5/HTML",
  "-18e4bdfc": "CSS3/CSS",
  "114bdd2b": "Javascript(Es6+)",
  "e1a3a35": "FRAMEWORKS",
  "-5c61e8f8": "ReactJs",
  "-749ad4f5": "NodeJs",
  "-6af96347": "ExpressJs",
  "7a1bc8c1": "Twitter Bootstrap",
  "-354c8953": "Materialize",
  "73ee47c9": "GraphQL",
  "4c4d1bb": "TOOLS",
  "4be7609a": "Postman",
  "-3e999248": "Adobe Creative Suite",
  "49b652a2": "Git Bash",
  "-688d79b6": "VSCode",
  "-2d9136a": "Jenkins",
  "2d4d14c4": "Think Clearly; Design freely; Code(Dry).",
  "19813f71": "ReactJs/ React Native",
  "-6bbca4ea": "Work together?",
  "-2aa56ad6": "Write an email",
  "-1c9ebcb9": "crafted by chizaram chinedu",
  "-7aba473": "Style Guide",
  "-30f1a6d": "Hero Text",
  "4263f57": "Hero1",
  "-4277bd4f": "headings",
  "6af22973": "Heading 1",
  "-79cbebcc": "Display 2",
  "6af22974": "Heading 2",
  "6af22975": "Heading 3",
  "6af22976": "Heading 4",
  "6af22977": "Heading 5",
  "6af22978": "Heading 6",
  "-7764bf1b": "Paragraphs",
  "5bc01acd": "Paragraph: ipsum dolor sit amet, consectetur adipiscing elit. Suspendisse varius enim in eros elementum tristique. Duis cursus, mi quis viverra ornare, eros dolor interdum nulla, ut commodo diam libero vitae erat. Aenean faucibus nibh et justo cursus id rutrum lorem imperdiet. Nunc ut sem vitae risus tristique posuere.",
  "-310dce09": "White Paragraph",
  "200d": "‍",
  "71e45d70": "Link with animation",
  "3610230d": "Text Link",
  "719b5761": "Buttons",
  "31bf12b3": "Black Button",
  "33870bf7": "Large Button",
  "41b289f1": "Rich Text",
  "-5fbf73a3": "Rich Txt H1",
  "-3c0dda4d": "What’s a Rich Text element?",
  "70087c26": "The rich text element allows you to create and format headings, paragraphs, blockquotes, images, and video all in one place instead of having to add and format them individually. Just double-click and easily create content.undefined",
  "-2d327b1d": "Some text with Heading 4",
  "5b5b6504": "Some text with heading 5",
  "5b5b6505": "Some text with heading 6",
  "-1a7f624": "Some bold text",
  "-277a680f": "Some Italic text",
  "-4d3e9f21": "Image Caption ",
  "-a016b40": "A rich text element can be used with static or dynamic content. For static content, just drop it into any page and begin editing. For dynamic content, add a rich text field to any collection and then connect a rich text element to that field in the settings panel. Voila!",
  "5bd70c04": "Quote - Headings, paragraphs, blockquotes, figures, images, and figure captions can all be styled after a class is added to the rich text element using the \"When inside of\" nested selector system.",
  "-518a07fb": "List item first",
  "3638c9bf": "List item second",
  "6ca2b4dd": "Numbered List item",
  "-722a5313": "chizaram@rd3studiosllc.com",
  "28aec5": "View",
  "-20e9cf80": "Dribbble",
  "145e1f47": "crafted by Chizaram Chinedu",
  "24737c59": "All Projects",
  "5707e367": "Study Case",
  "293b31": "Work",
  "7877dfeb": "Client",
  "75a5bdd6": "Awards",
  "-41346436": "Other Projects",
  "-2c81ed34": "My selected art-work",
  "-60ddc9d6": "Welcome to a glimpse of mymind¯\\_(ツ)_/¯",
  "3256e4d2": "For the last 5 years, I've been freelancing and getting my hands dirty working in both startups and established companies.",
  "-608af1a": "My favorite  tools are are VSCode, Webflow and Grammerly :-). ",
  "-29f12ff0": "I know a thing or two. Description still loading ",
  "-3ff8f1fe": "Design ",
  "12e920": "(01)",
  "5282e132": "Lorem ipsum dolor sit amet, consectetur adipiscing elit. Cras et vehicula leo, vitae pharetra tortor. Morbi facilisis vehicula commodo.",
  "79cfaa7d": "DevOps",
  "12e93f": "(02)",
  "-164f3c49": "Soccer ",
  "12e95e": "(03)",
  "-687770a7": "Mauris egestas et quam vel convallis. Nullam dui purus, auctor id mauris a, mattis rutrum nisi.",
  "6fbef0eb": "Second home",
  "-416091a0": "#brand to be remembered",
  "65814a80": "Taking a photo of my self",
  "457db44c": "Dark and Black",
  "4633de": "Library of the city",
  "74d3e96f": "@chizwils",
  "1df40fe9": "Here are some of my instagram ",
  "565c31cb": "“bangers”",
  "5bccbfc0": "What a view",
  "71b8358a": "Experience",
  "78d0fcf8": "Peaceful #peace #positive",
  "-3ce86cc3": "Me Riding",
  "5834dbe0": "My favorite instagram picture",
  "-11d4bbff": "Protected Page",
  "-f5c4b5f": "Incorrect password. Please try again.",
  "-40b0787c": "Page Not Found",
  "583f3656": "The page you are looking for doesn't exist or has been moved.",
  "679ac74": "All posts",
  "-3be6a73c": "Category: ",
  "31997f7f": "Read more",
  "-4237c9f3": "You can read my mind",
  "1cff94b4": "Sign up for my newsletter",
  "-6a7660fe": "Monthlly hand-piced design inspirations and stores of thriving new creatives",
  "33b7d778": "Thank you!",
  "-7c112e99": "Oops! Something went wrong while submitting the form.",
  "-25f0b863": "Say hello, i’d love to say hi back",
  "434317a8": "Thank you! ",
  "-4fec8807": "Your submission has been received!",
  "-858b12c": "Change Log",
  "-564cc93e": "Ver. 1.0 ",
  "-1787da6": "(Nov 2020)",
  "-34061915": "Initial Release",
  "-38ad4b62": "Licensing",
  "3936918e": "Assests",
  "10fc3be6": "All graphical assets in this template are licensed for personal and commercial use. If you’d like to use a specific asset, please check the license below",
  "74d71b5a": "Unshplash - Photos for everyone",
  "4ed5d2b": "Visit",
  "-3786bcaa": "Feather - a collection of simply beautiful open source icons.",
  "6e047936": "Google Fonts - Manrope"
}